txtools/__init__.py
txtools/clusterer.py
txtools/normalizer.py
txtools/similarity.py
txtools/utils.py
txtools/vectorizer.py
texcptulz-2.5.0.dist-info/LICENSE
texcptulz-2.5.0.dist-info/METADATA
texcptulz-2.5.0.dist-info/WHEEL
texcptulz-2.5.0.dist-info/top_level.txt
texcptulz-2.5.0.dist-info/RECORD
