Metadata-Version: 2.1
Name: texcptulz
Version: 2.5.0
Summary: Tools for cleaning and preprocessing text
Home-page: https://github.com/fdelgados/Textools.git
Author: Cisco Delgado
Author-email: fdelgados@gmail.com
License: UNKNOWN
Platform: UNKNOWN
Classifier: Programming Language :: Python :: 3
Classifier: License :: OSI Approved :: MIT License
Classifier: Operating System :: OS Independent
Requires-Python: >=3.5
Requires-Dist: nltk
Requires-Dist: scikit-learn
Requires-Dist: spacy
Requires-Dist: spacy-langdetect
Requires-Dist: gensim
Requires-Dist: numpy
